ticketpy/__init__.py
ticketpy/client.py
ticketpy/model.py
ticketpy/query.py
ticketpy-1.1.2.dist-info/DESCRIPTION.rst
ticketpy-1.1.2.dist-info/METADATA
ticketpy-1.1.2.dist-info/RECORD
ticketpy-1.1.2.dist-info/WHEEL
ticketpy-1.1.2.dist-info/metadata.json
ticketpy-1.1.2.dist-info/top_level.txt
