Metadata-Version: 1.0
Name: ticketpy
Version: 1.1.2
Summary: Python wrapper/SDK for the Ticketmaster Discovery API
Home-page: https://github.com/arcward/ticketpy
Author: Edward Wells
Author-email: git@edward.sh
License: MIT
Keywords: Ticketmaster
Platform: UNKNOWN
